py_adsb_historical_data_client/__init__.py
py_adsb_historical_data_client/historical.py
py_adsb_historical_data_client/logger_config.py
py_adsb_historical_data_client/py.typed
py_adsb_historical_data_client-0.3.5.dist-info/METADATA
py_adsb_historical_data_client-0.3.5.dist-info/WHEEL
py_adsb_historical_data_client-0.3.5.dist-info/licenses/LICENSE
py_adsb_historical_data_client-0.3.5.dist-info/RECORD
