Metadata-Version: 2.4
Name: py-adsb-historical-data-client
Version: 0.3.5
Summary: Add your description here
Author-email: Alexis Placet <placet.alexis+pypi@protonmail.com>
License-File: LICENSE
Requires-Python: >=3.12
Requires-Dist: numpy>=2.3.1
Requires-Dist: pyreadsb>=1.3.2
Requires-Dist: requests>=2.32.4
Requires-Dist: types-requests>=2.32.4.20250611
